Workbook

Sheet Buchungen
A1: 2025 aqua cloud
A3: Konto/BWA | B3: Datum | C3: Buchungstext | D3: Belegfeld1 | E3: Ausgaben | F3: Einnahmen | G3: Kostenstellen | H3: Leistungsdatum | I3: Kostenstelle
A4: 5900 | B4: 45672 | C4: Technext - Software Engineer 01.2025 | D4: 20240115004 | E4: 1931.99 | G4: 201 | I4: =VLOOKUP(G4,Kostenstellen!$A$1:$C$17,2,0) -> indirekte
A5: 5900 | B5: 45689 | C5: Shevchenko 01.2025 | D5: 010522-250201 | E5: 79.5 | G5: 210 | H5: 45688 | I5: =VLOOKUP(G5,Kostenstellen!$A$1:$C$17,2,0) -> Dev
A6: 5900 | B6: 45689 | C6: Bessmertnyy 01.2025 | D6: 041021-250201 | E6: 2740 | G6: 210 | H6: 45688 | I6: =VLOOKUP(G6,Kostenstellen!$A$1:$C$17,2,0) -> Dev
A7: 5900 | B7: 45689 | C7: Marynkevych 01.2025 | D7: 090124-250201 | E7: 6300 | G7: 210 | H7: 45688 | I7: =VLOOKUP(G7,Kostenstellen!$A$1:$C$17,2,0) -> Dev
A8: 5900 | B8: 45689 | C8: MZA 01.2025 | D8: 091023-250201 | E8: 5000 | G8: 210 | H8: 45688 | I8: =VLOOKUP(G8,Kostenstellen!$A$1:$C$17,2,0) -> Dev
A9: 5900 | B9: 45689 | C9: Madiyar Solutions 01.2025 | D9: 091224-250201 | E9: 3200 | G9: 210 | H9: 45688 | I9: =VLOOKUP(G9,Kostenstellen!$A$1:$C$17,2,0) -> Dev
A10: 5900 | B10: 45689 | C10: Savchenko 01.2025 | D10: 130125-250203 | E10: 2175 | G10: 210 | H10: 45688 | I10: =VLOOKUP(G10,Kostenstellen!$A$1:$C$17,2,0) -> Dev
A11: 5900 | B11: 45689 | C11: Weissgerber 01.2025 | D11: 160924-250201 | E11: 4500 | G11: 210 | H11: 45688 | I11: =VLOOKUP(G11,Kostenstellen!$A$1:$C$17,2,0) -> Dev
A12: 5900 | B12: 45689 | C12: Chebyshev 01.2025 | D12: 201222-250201 | E12: 1200 | G12: 210 | H12: 45688 | I12: =VLOOKUP(G12,Kostenstellen!$A$1:$C$17,2,0) -> Dev
A13: 5900 | B13: 45689 | C13: Shuja 01.2025 | D13: 220701-250201 | E13: 3772 | G13: 210 | H13: 45688 | I13: =VLOOKUP(G13,Kostenstellen!$A$1:$C$17,2,0) -> Dev
A14: 5900 | B14: 45689 | C14: Almasi 01.2025 | D14: 220702-250201 | E14: 4232 | G14: 210 | H14: 45688 | I14: =VLOOKUP(G14,Kostenstellen!$A$1:$C$17,2,0) -> Dev
A15: 5900 | B15: 45689 | C15: Kazymov 01.2025 | D15: 230924-250201 | E15: 2800 | G15: 210 | H15: 45688 | I15: =VLOOKUP(G15,Kostenstellen!$A$1:$C$17,2,0) -> Dev
A16: 5900 | B16: 45689 | C16: Chadin 01.2025 | D16: 25180422-250201 | E16: 1700 | G16: 210 | H16: 45688 | I16: =VLOOKUP(G16,Kostenstellen!$A$1:$C$17,2,0) -> Dev
... A19: 5900 | B19: 45691 | C19: Mykhailov 01.2025 | D19: 060125-250203 | E19: 2454.54 | G19: 220 | H19: 45688 | I19: =VLOOKUP(G19,Kostenstellen!$A$1:$C$17,2,0) -> Product
A20: 5900 | B20: 45692 | C20: andagon people - Schulung | D20: 20252000041 | E20: 3198 | G20: 200 | I20: =VLOOKUP(G20,Kostenstellen!$A$1:$C$17,2,0) -> aqua
A21: 5900 | B21: 45703 | C21: Technext - Software Engineer 02.2025 | D21: 20250215005 | E21: 1925.48 | G21: 201 | I21: =VLOOKUP(G21,Kostenstellen!$A$1:$C$17,2,0) -> indirekte
A22: 5900 | B22: 45717 | C22: Bessmertnyy 02.2025 | D22: 041021-250301 | E22: 2740 | G22: 210 | H22: 45689 | I22: =VLOOKUP(G22,Kostenstellen!$A$1:$C$17,2,0) -> Dev
A23: 5900 | B23: 45717 | C23: Mykhailov 02.2025 | D23: 060125-250301 | E23: 2700 | G23: 220 | H23: 45689 | I23: =VLOOKUP(G23,Kostenstellen!$A$1:$C$17,2,0) -> Product
A24: 5900 | B24: 45717 | C24: Marynkevych 02.2025 | D24: 090124-250301 | E24: 6300 | G24: 210 | H24: 45689 | I24: =VLOOKUP(G24,Kostenstellen!$A$1:$C$17,2,0) -> Dev
A25: 5900 | B25: 45717 | C25: MZA 02.2025 | D25: 091023-250301 | E25: 5000 | G25: 210 | H25: 45716 | I25: =VLOOKUP(G25,Kostenstellen!$A$1:$C$17,2,0) -> Dev
A26: 5900 | B26: 45717 | C26: Madiyar Solutions 02.2025 | D26: 091224-250301 | E26: 3200 | G26: 210 | H26: 45689 | I26: =VLOOKUP(G26,Kostenstellen!$A$1:$C$17,2,0) -> Dev
A27: 5900 | B27: 45717 | C27: Savchenko 02.2025 | D27: 130125-250301 | E27: 2900 | G27: 210 | H27: 45689 | I27: =VLOOKUP(G27,Kostenstellen!$A$1:$C$17,2,0) -> Dev
A28: 5900 | B28: 45717 | C28: Weissgerber 02.2025 | D28: 160924-250301 | E28: 4500 | G28: 210 | H28: 45716 | I28: =VLOOKUP(G28,Kostenstellen!$A$1:$C$17,2,0) -> Dev
A29: 5900 | B29: 45717 | C29: 02.2025 Chebyshev | D29: 201222-250301 | E29: 1200 | G29: 210 | H29: 45716 | I29: =VLOOKUP(G29,Kostenstellen!$A$1:$C$17,2,0) -> Dev
A30: 5900 | B30: 45717 | C30: Shuja 02.2025 | D30: 220701-250301 | E30: 3280 | G30: 210 | H30: 45716 | I30: =VLOOKUP(G30,Kostenstellen!$A$1:$C$17,2,0) -> Dev
A31: 5900 | B31: 45717 | C31: 02.2025 Almasi | D31: 220702-250301 | E31: 3680 | G31: 210 | H31: 45716 | I31: =VLOOKUP(G31,Kostenstellen!$A$1:$C$17,2,0) -> Dev
A32: 5900 | B32: 45717 | C32: Kazymov 02.2025 | D32: 230924-250301 | E32: 2800 | G32: 210 | H32: 45689 | I32: =VLOOKUP(G32,Kostenstellen!$A$1:$C$17,2,0) -> Dev
A33: 5900 | B33: 45717 | C33: Chadin 02.2025 | D33: 25180422-250301 | E33: 1749.7 | G33: 210 | H33: 45689 | I33: =VLOOKUP(G33,Kostenstellen!$A$1:$C$17,2,0) -> Dev
... A35: 5900 | B35: 45717 | C35: Mashynson 02.2025 | D35: 290724-250301 | E35: 2800 | G35: 210 | H35: 45689 | I35: =VLOOKUP(G35,Kostenstellen!$A$1:$C$17,2,0) -> Dev
A36: 5900 | B36: 45730 | C36: andagon people - Schulung 07.2025 | D36: 20252000107 | E36: 1599 | G36: 200 | I36: =VLOOKUP(G36,Kostenstellen!$A$1:$C$17,2,0) -> aqua
A37: 5900 | B37: 45730 | C37: andagon people - Schulung 07.2025 | D37: 20252000108 | E37: 1599 | G37: 200 | I37: =VLOOKUP(G37,Kostenstellen!$A$1:$C$17,2,0) -> aqua
A38: 5900 | B38: 45731 | C38: Technext - Software Engineer 03.2025 | D38: 20250315010 | E38: 1873.27 | G38: 201 | I38: =VLOOKUP(G38,Kostenstellen!$A$1:$C$17,2,0) -> indirekte
A39: 5900 | B39: 45748 | C39: Bessmertnyy 03.2025 | D39: 041021-250401 | E39: 1724 | G39: 210 | H39: 45717 | I39: =VLOOKUP(G39,Kostenstellen!$A$1:$C$17,2,0) -> Dev
A40: 5900 | B40: 45748 | C40: Mykhailov 03.2025 | D40: 060125-250401 | E40: 2700 | G40: 220 | H40: 45717 | I40: =VLOOKUP(G40,Kostenstellen!$A$1:$C$17,2,0) -> Product
A41: 5900 | B41: 45748 | C41: Marynkevych 03.2025 | D41: 090124-250401 | E41: 6300 | G41: 210 | H41: 45717 | I41: =VLOOKUP(G41,Kostenstellen!$A$1:$C$17,2,0) -> Dev
A42: 5900 | B42: 45748 | C42: MZA 03.2025 | D42: 091023-250401 | E42: 5000 | G42: 210 | H42: 45717 | I42: =VLOOKUP(G42,Kostenstellen!$A$1:$C$17,2,0) -> Dev
A43: 5900 | B43: 45748 | C43: Madiyar Solutions 03.2025 | D43: 091224-250401 | E43: 3200 | G43: 210 | H43: 45717 | I43: =VLOOKUP(G43,Kostenstellen!$A$1:$C$17,2,0) -> Dev
A44: 5900 | B44: 45748 | C44: Savchenko 03.2025 | D44: 130125-250401 | E44: 2900 | G44: 210 | H44: 45717 | I44: =VLOOKUP(G44,Kostenstellen!$A$1:$C$17,2,0) -> Dev
A45: 5900 | B45: 45748 | C45: Weissgerber 03.2025 | D45: 160924-250401 | E45: 4500 | G45: 210 | H45: 45717 | I45: =VLOOKUP(G45,Kostenstellen!$A$1:$C$17,2,0) -> Dev
A46: 5900 | B46: 45748 | C46: Chebyshev 03.2025 | D46: 201222-250401 | E46: 1200 | G46: 210 | H46: 45717 | I46: =VLOOKUP(G46,Kostenstellen!$A$1:$C$17,2,0) -> Dev
A47: 5900 | B47: 45748 | C47: Shuja 03.2025 | D47: 220701-250401 | E47: 3444 | G47: 210 | H47: 45717 | I47: =VLOOKUP(G47,Kostenstellen!$A$1:$C$17,2,0) -> Dev
A48: 5900 | B48: 45748 | C48: Almasi 03.2025 | D48: 220702-250401 | E48: 3864 | G48: 210 | H48: 45717 | I48: =VLOOKUP(G48,Kostenstellen!$A$1:$C$17,2,0) -> Dev
A49: 5900 | B49: 45748 | C49: Kazymov 03.2025 | D49: 230924-250401 | E49: 2800 | G49: 210 | H49: 45717 | I49: =VLOOKUP(G49,Kostenstellen!$A$1:$C$17,2,0) -> Dev
A50: 5900 | B50: 45748 | C50: Chadin 03.2025 | D50: 25180422-250401 | E50: 1747.9 | G50: 210 | H50: 45717 | I50: =VLOOKUP(G50,Kostenstellen!$A$1:$C$17,2,0) -> Dev
... A52: 5900 | B52: 45748 | C52: Mashynson 03.2025 | D52: 290724-250401 | E52: 2800 | G52: 210 | H52: 45717 | I52: =VLOOKUP(G52,Kostenstellen!$A$1:$C$17,2,0) -> Dev
A53: 5900 | B53: 45762 | C53: Technext - Software Engineer 04.2025 | D53: 20250415009 | E53: 1771.02 | G53: 201 | I53: =VLOOKUP(G53,Kostenstellen!$A$1:$C$17,2,0) -> indirekte
A54: 5900 | B54: 45778 | C54: Edhars Ternovyi 04.2025 | D54: 010321-250501 | E54: 913.1 | G54: 235 | H54: 45748 | I54: =VLOOKUP(G54,Kostenstellen!$A$1:$C$17,2,0) -> Marketing
A55: 5900 | B55: 45778 | C55: Mykhailov 04.2025 | D55: 060125-250501 | E55: 2700 | G55: 220 | H55: 45748 | I55: =VLOOKUP(G55,Kostenstellen!$A$1:$C$17,2,0) -> Product
A56: 5900 | B56: 45778 | C56: Marynkevych 04.2025 | D56: 090124-250501 | E56: 6300 | G56: 210 | H56: 45748 | I56: =VLOOKUP(G56,Kostenstellen!$A$1:$C$17,2,0) -> Dev
A57: 5900 | B57: 45778 | C57: MZA 04.2025 | D57: 091023-250505 | E57: 5000 | G57: 210 | H57: 45748 | I57: =VLOOKUP(G57,Kostenstellen!$A$1:$C$17,2,0) -> Dev
A58: 5900 | B58: 45778 | C58: Madiyar Solutions 04.2025 | D58: 091224-250501 | E58: 3054.54 | G58: 210 | H58: 45748 | I58: =VLOOKUP(G58,Kostenstellen!$A$1:$C$17,2,0) -> Dev
A59: 5900 | B59: 45778 | C59: Savchenko 04.2025 | D59: 130125-250501 | E59: 2900 | G59: 210 | H59: 45748 | I59: =VLOOKUP(G59,Kostenstellen!$A$1:$C$17,2,0) -> Dev
A60: 5900 | B60: 45778 | C60: Weissgerber 04.2025 | D60: 160924-250501 | E60: 4500 | G60: 210 | H60: 45748 | I60: =VLOOKUP(G60,Kostenstellen!$A$1:$C$17,2,0) -> Dev
A61: 5900 | B61: 45778 | C61: Chebyshev 04.2025 | D61: 201222-250501 | E61: 1200 | G61: 210 | H61: 45748 | I61: =VLOOKUP(G61,Kostenstellen!$A$1:$C$17,2,0) -> Dev
A62: 5900 | B62: 45778 | C62: Shuja 04.2025 | D62: 220701-250501 | E62: 3608 | G62: 210 | H62: 45748 | I62: =VLOOKUP(G62,Kostenstellen!$A$1:$C$17,2,0) -> Dev
A63: 5900 | B63: 45778 | C63: Almasi 04.2025 | D63: 220702-250501 | E63: 4048 | G63: 210 | H63: 45748 | I63: =VLOOKUP(G63,Kostenstellen!$A$1:$C$17,2,0) -> Dev
A64: 5900 | B64: 45778 | C64: Kazymov 04.2025 | D64: 230924-250501 | E64: 2800 | G64: 210 | H64: 45748 | I64: =VLOOKUP(G64,Kostenstellen!$A$1:$C$17,2,0) -> Dev
A65: 5900 | B65: 45778 | C65: Chadin 04.2025 | D65: 25180422-250501 | E65: 1739 | G65: 210 | H65: 45748 | I65: =VLOOKUP(G65,Kostenstellen!$A$1:$C$17,2,0) -> Dev
... A67: 5900 | B67: 45778 | C67: Mashynson 04.2025 | D67: 290724-250501 | E67: 2672.73 | G67: 210 | H67: 45748 | I67: =VLOOKUP(G67,Kostenstellen!$A$1:$C$17,2,0) -> Dev
A68: 5900 | B68: 45792 | C68: Technext - Software Engineer 05.2025 | D68: 20250515004 | E68: 1340 | G68: 201 | I68: =VLOOKUP(G68,Kostenstellen!$A$1:$C$17,2,0) -> indirekte
A69: 5900 | B69: 45809 | C69: Mykhailov 05.2025 | D69: 060125-250601 | E69: 2700 | G69: 220 | H69: 45778 | I69: =VLOOKUP(G69,Kostenstellen!$A$1:$C$17,2,0) -> Product
A70: 5900 | B70: 45809 | C70: Marynkevych 05.2025 | D70: 090124-250601 | E70: 6300 | G70: 210 | H70: 45778 | I70: =VLOOKUP(G70,Kostenstellen!$A$1:$C$17,2,0) -> Dev
A71: 5900 | B71: 45809 | C71: MZA 05.2025 | D71: 091023-250601 | E71: 5000 | G71: 210 | H71: 45808 | I71: =VLOOKUP(G71,Kostenstellen!$A$1:$C$17,2,0) -> Dev
A72: 5900 | B72: 45809 | C72: Savchenko 05.2025 | D72: 130125-250601 | E72: 2900 | G72: 210 | H72: 45778 | I72: =VLOOKUP(G72,Kostenstellen!$A$1:$C$17,2,0) -> Dev
A73: 5900 | B73: 45809 | C73: Weissgerber 05.2025 | D73: 160924-250601 | E73: 4500 | G73: 210 | H73: 45808 | I73: =VLOOKUP(G73,Kostenstellen!$A$1:$C$17,2,0) -> Dev
A74: 5900 | B74: 45809 | C74: Chebyshev 05.2025 | D74: 201222-250601 | E74: 1200 | G74: 210 | H74: 45808 | I74: =VLOOKUP(G74,Kostenstellen!$A$1:$C$17,2,0) -> Dev
A75: 5900 | B75: 45809 | C75: Shuja 05.2025 | D75: 220701-250601 | E75: 3608 | G75: 210 | H75: 45808 | I75: =VLOOKUP(G75,Kostenstellen!$A$1:$C$17,2,0) -> Dev
A76: 5900 | B76: 45809 | C76: Almasi 05.2025 | D76: 220702-250601 | E76: 4048 | G76: 210 | H76: 45808 | I76: =VLOOKUP(G76,Kostenstellen!$A$1:$C$17,2,0) -> Dev
A77: 5900 | B77: 45809 | C77: Kazymov 05.2025 | D77: 230924-250601 | E77: 2800 | G77: 210 | H77: 45778 | I77: =VLOOKUP(G77,Kostenstellen!$A$1:$C$17,2,0) -> Dev
A78: 5900 | B78: 45809 | C78: Chadin 05.2025 | D78: 25180422-250601 | E78: 1739 | G78: 210 | H78: 45778 | I78: =VLOOKUP(G78,Kostenstellen!$A$1:$C$17,2,0) -> Dev
A79: 5900 | B79: 45809 | C79: Vetkhov 05.2025 | D79: 270323-250601 | E79: 714 | G79: 210 | H79: 45778 | I79: =VLOOKUP(G79,Kostenstellen!$A$1:$C$17,2,0) -> Dev
A80: 5900 | B80: 45809 | C80: Mashynson 05.2025 | D80: 290724-250601 | E80: 2800 | G80: 210 | H80: 45808 | I80: =VLOOKUP(G80,Kostenstellen!$A$1:$C$17,2,0) -> Dev
A81: 5900 | B81: 45810 | C81: Buhun 05.2025 | D81: 120525-250602 | E81: 3000 | G81: 210 | H81: 45778 | I81: =VLOOKUP(G81,Kostenstellen!$A$1:$C$17,2,0) -> Dev
A82: 5900 | B82: 45823 | C82: Technext - Software Engineer 06.2025 | D82: 202506006 | E82: 889.29 | G82: 201 | I82: =VLOOKUP(G82,Kostenstellen!$A$1:$C$17,2,0) -> indirekte
A83: 5900 | B83: 45839 | C83: Edhars Ternovyi 06.2025 | D83: 010321-250701 | E83: 671.75 | G83: 235 | H83: 45838 | I83: =VLOOKUP(G83,Kostenstellen!$A$1:$C$17,2,0) -> Marketing
A84: 5900 | B84: 45839 | C84: Panko 06.2025 | D84: 020625-250701 | E84: 3300 | G84: 220 | H84: 45838 | I84: =VLOOKUP(G84,Kostenstellen!$A$1:$C$17,2,0) -> Product
A85: 5900 | B85: 45839 | C85: Mykhalov 06.2025 | D85: 060125-250701 | E85: 2700 | G85: 220 | H85: 45838 | I85: =VLOOKUP(G85,Kostenstellen!$A$1:$C$17,2,0) -> Product
A86: 5900 | B86: 45839 | C86: Marynkevych 06.2025 | D86: 090124-250701 | E86: 6300 | G86: 210 | H86: 45838 | I86: =VLOOKUP(G86,Kostenstellen!$A$1:$C$17,2,0) -> Dev
A87: 5900 | B87: 45839 | C87: MZA 06.2025 | D87: 091023-250701 | E87: 5000 | G87: 210 | H87: 45838 | I87: =VLOOKUP(G87,Kostenstellen!$A$1:$C$17,2,0) -> Dev
A88: 5900 | B88: 45839 | C88: Buhun 06.2025 | D88: 120525-250701 | E88: 4000 | G88: 210 | H88: 45838 | I88: =VLOOKUP(G88,Kostenstellen!$A$1:$C$17,2,0) -> Dev
A89: 5900 | B89: 45839 | C89: Savchenko 06.2025 | D89: 130125-250701 | E89: 2900 | G89: 210 | H89: 45838 | I89: =VLOOKUP(G89,Kostenstellen!$A$1:$C$17,2,0) -> Dev
A90: 5900 | B90: 45839 | C90: Weissgerber 06.2025 | D90: 160924-250701 | E90: 4500 | G90: 210 | H90: 45838 | I90: =VLOOKUP(G90,Kostenstellen!$A$1:$C$17,2,0) -> Dev
A91: 5900 | B91: 45839 | C91: Chebyshev 06.2025 | D91: 201222-250701 | E91: 1200 | G91: 210 | H91: 45838 | I91: =VLOOKUP(G91,Kostenstellen!$A$1:$C$17,2,0) -> Dev
A92: 5900 | B92: 45839 | C92: Shuja 06.2025 | D92: 220701-250701 | E92: 2624 | G92: 210 | H92: 45838 | I92: =VLOOKUP(G92,Kostenstellen!$A$1:$C$17,2,0) -> Dev
A93: 5900 | B93: 45839 | C93: Almasi 06.2025 | D93: 220702-250701 | E93: 3864 | G93: 210 | H93: 45838 | I93: =VLOOKUP(G93,Kostenstellen!$A$1:$C$17,2,0) -> Dev
A94: 5900 | B94: 45839 | C94: Kazymov 06.2025 | D94: 230924-250701 | E94: 2800 | G94: 210 | H94: 45838 | I94: =VLOOKUP(G94,Kostenstellen!$A$1:$C$17,2,0) -> Dev
... A97: 5900 | B97: 45839 | C97: Mashynson 06.2025 | D97: 290724-250701 | E97: 2800 | G97: 210 | H97: 45838 | I97: =VLOOKUP(G97,Kostenstellen!$A$1:$C$17,2,0) -> Dev
A98: 5900 | B98: 45846 | C98: andagon people - Schulung 07.2025 | D98: 20252000293 | E98: 1599 | G98: 200 | I98: =VLOOKUP(G98,Kostenstellen!$A$1:$C$17,2,0) -> aqua
A99: 5900 | B99: 45853 | C99: Technext - Software Engineer 07.2025 | D99: 20250715003 | E99: 899.07 | G99: 201 | I99: =VLOOKUP(G99,Kostenstellen!$A$1:$C$17,2,0) -> indirekte
A100: 5900 | B100: 45870 | C100: Panko 07.2025 | D100: 020625-250801 | E100: 3300 | G100: 220 | H100: 45839 | I100: =VLOOKUP(G100,Kostenstellen!$A$1:$C$17,2,0) -> Product
A101: 5900 | B101: 45870 | C101: Mykhalov 07.2025 | D101: 060125-250801 | E101: 2700 | G101: 220 | H101: 45839 | I101: =VLOOKUP(G101,Kostenstellen!$A$1:$C$17,2,0) -> Product
A102: 5900 | B102: 45870 | C102: Marynkevych 07.2025 | D102: 090124-250801 | E102: 6300 | G102: 210 | H102: 45839 | I102: =VLOOKUP(G102,Kostenstellen!$A$1:$C$17,2,0) -> Dev
A103: 5900 | B103: 45870 | C103: MZA 07.2025 | D103: 091023-250801 | E103: 5000 | G103: 210 | H103: 45839 | I103: =VLOOKUP(G103,Kostenstellen!$A$1:$C$17,2,0) -> Dev
A104: 5900 | B104: 45870 | C104: Buhun 07.2025 | D104: 120525-250801 | E104: 4000 | G104: 210 | H104: 45869 | I104: =VLOOKUP(G104,Kostenstellen!$A$1:$C$17,2,0) -> Dev
A105: 5900 | B105: 45870 | C105: Savchenko 07.2025 | D105: 130125-250801 | E105: 2900 | G105: 210 | H105: 45839 | I105: =VLOOKUP(G105,Kostenstellen!$A$1:$C$17,2,0) -> Dev
A106: 5900 | B106: 45870 | C106: Bendyk 07.2025 | D106: 160725-250801 | E106: 2181.82 | G106: 210 | H106: 45839 | I106: =VLOOKUP(G106,Kostenstellen!$A$1:$C$17,2,0) -> Dev
A107: 5900 | B107: 45870 | C107: Malyk 07.2025 | D107: 160725-250801 | E107: 1909 | G107: 210 | H107: 45839 | I107: =VLOOKUP(G107,Kostenstellen!$A$1:$C$17,2,0) -> Dev
A108: 5900 | B108: 45870 | C108: Weissgerber 07.2025 | D108: 160924-250801 | E108: 4500 | G108: 210 | H108: 45839 | I108: =VLOOKUP(G108,Kostenstellen!$A$1:$C$17,2,0) -> Dev
...

Sheet BWA
A1: Kanzlei-Rechnungswesen - RW - 358875/10530/2025 / aqua cloud GmbH - [BWA-Nr. 1 - Wertenachweis Kurzfristige Erfolgsrechnung Dezember 2025]
A2: Zeile | B2: Bezeichnung | C2: Konto | E2: Zeile | F2: Konten-/ Zeilenbeschriftung | G2: Dez/2025 _x000D_Konten/Zeilen | H2: BWA-Werte | I2: Jan/2025-Dez/2025 _x000D_Konten/Zeilen | J2: BWA-Werte | K2: Fkt.-Schl.
A3: 1020 | B3: Umsatzerlöse | C3: 4337 | D3: H | F3: Erlöse aus Leistungen nach § 13b UStG | G3: 10330.66 | H3: 188239.89 | I3: 94337.58 | J3: 2187895.4 | K3: 0
A4: 1020 | C4: 4338 | D4: H | F4: Nicht steuerbare Umsätze Drittland | G4: 23132.36 | I4: 188898.92 | K4: 0
A5: 1020 | C5: 4402 | D5: H | F5: Erlöse aqua Miete/SaaS | G5: 68145.25 | I5: 734549.96 | K5: 0
A6: 1020 | C6: 4403 | D6: H | F6: Erlöse 19% USt aqua Kauf | G6: 18327.76 | I6: 372074.58 | K6: 0
A7: 1020 | C7: 4406 | D7: H | F7: Erlöse aqua sonstige | G7: 10000 | I7: 32749 | K7: 0
A8: 1020 | C8: 4409 | D8: H | F8: Erlöse aqua M&S | G8: 58303.86 | I8: 701355.39 | K8: 0
A9: 1020 | C9: 4410 | D9: H | F9: Erlöse Fremdlizenzen | G9: 0 | I9: 63930 | K9: 0
A10: 1020 | C10: 0
A11: 1051 | B11: Gesamtleistung | C11: 0 | E11: 1020 | F11: Umsatzerlöse | G11: 188239.89 | H11: 188239.89 | I11: 2187895.4 | J11: 2187895.4 | K11: 1
A12: 1051 | C12: 0
A13: 1060 | B13: Mat./Wareneinkauf | C13: 5900 | D13: S | F13: Fremdleistungen | G13: 9260 | H13: 9260 | I13: 525900.66 | J13: 612970.67 | K13: 25
A14: 1060 | C14: 5901 | D14: S | F14: Fremdleistund AI | G14: 0 | I14: 36400 | K14: 25
A15: 1060 | C15: 5923 | D15: S | F15: Sonstige Leistungen EU 19% Vorst./USt | G15: 0 | I15: 50670.01 | K15: 25
A16: 1060 | C16: 0
A17: 1080 | B17: Rohertrag | C17: 0 | E17: 1051 | F17: Gesamtleistung | G17: 188239.89 | H17: 178979.89 | I17: 2187895.4 | J17: 1574924.8 | K17: 2
A18: 1080 | C18: 0 | E18: 1060 | F18: Mat./Wareneinkauf | G18: 9260 | I18: 612970.67 | K18: 2
A19: 1080 | C19: 0
A20: 1090 | B20: So. betr. Erlöse | C20: 4830 | D20: H | F20: Sonstige betriebliche Erträge | G20: 0 | H20: 929.85 | I20: 831.67 | J20: 16228.65 | K20: 0
A21: 1090 | C21: 4840 | D21: H | F21: Erträge aus der Währungsumrechnung | G21: 0 | I21: 0.92 | K21: 0
A22: 1090 | C22: 4946 | D22: H | F22: Verrechnete sonstige Sachbezüge | G22: -28 | I22: 4395.65 | K22: 0
A23: 1090 | C23: 4947 | D23: H | F23: Verrech. sonstige Sachbezüge Fzg 19% USt | G23: 957.85 | I23: 11000.41 | K23: 0
A24: 1090 | C24: 0
A25: 1092 | B25: Betriebl. Rohertrag | C25: 0 | E25: 1080 | F25: Rohertrag | G25: 178979.89 | H25: 179909.74 | I25: 1574924.8 | J25: 1591153.4 | K25: 1
A26: 1092 | C26: 0 | E26: 1090 | F26: So. betr. Erlöse | G26: 929.85 | I26: 16228.65 | K26: 1
A27: 1092 | C27: 0
A28: 1100 | B28: Personalkosten | C28: 6020 | D28: S | F28: Gehälter | G28: 41468.6 | H28: 52055.99 | I28: 476397.87 | J28: 606428.88 | K28: 0
A29: 1100 | C29: 6039 | D29: S | F29: Pauschale Steuer für Arbeitnehmer | G29: 0 | I29: 1540.23 | K29: 0
A30: 1100 | C30: 6060 | D30: S | F30: Freiwillige soziale Aufwendung. LSt-pfl. | G30: 0 | I30: 5409.75 | K30: 0
A31: 1100 | C31: 6072 | D31: S | F31: Sachzuwendungen und Dienstleistg. an AN | G31: 559 | I31: 6474 | K31: 0
A32: 1100 | C32: 6090 | D32: S | F32: Fahrtkostenerstatt. Whg./Arbeitsstätte | G32: 29.92 | I32: 241.2 | K32: 0
A33: 1100 | C33: 6110 | D33: S | F33: Gesetzliche Sozialaufwendungen | G33: 8655.1 | I33: 99409.49 | K33: 0
A34: 1100 | C34: 6120 | D34: S | F34: Beiträge zur Berufsgenossenschaft | G34: 0 | I34: 1221.73 | K34: 0
A35: 1100 | C35: 6130 | D35: S | F35: Freiwillige soziale Aufwendung. LSt-frei | G35: 589.37 | I35: 6884.11 | K35: 0
A36: 1100 | C36: 6140 | D36: S | F36: Aufwendungen für Altersversorgung | G36: 754 | I36: 8850.5 | K36: 0
A37: 1100 | C37: 0
A38: 1150 | B38: Versich./Beiträge | C38: 6400 | D38: S | F38: Versicherungen | G38: 509.9 | H38: 8134.82 | I38: 4059.4 | J38: 89299.95 | K38: 0
A39: 1150 | C39: 6420 | D39: S | F39: Beiträge | G39: 0 | I39: 300.56 | K39: 0
A40: 1150 | C40: 6421 | D40: S | F40: HR other | G40: 0 | I40: 2776.91 | K40: 0
A41: 1150 | C41: 6423 | D41: S | F41: Beiträge, Lizenzen (Marketing) | G41: 0 | I41: 1800 | K41: 0
A42: 1150 | C42: 6425 | D42: S | F42: Lizenzgebühren | G42: 7624.92 | I42: 80363.08 | K42: 0
A43: 1150 | C43: 0
A44: 1180 | B44: Fahrzeugko. (o. St) | C44: 6530 | D44: S | F44: Laufende Fahrzeug-Betriebskosten | G44: 1415.83 | H44: 1415.83 | I44: 20955.98 | J44: 20955.98 | K44: 0
A45: 1180 | C45: 0
A46: 1200 | B46: Werbe-/Reisekosten | C46: 6601 | D46: S | F46: Marketing content | G46: 0 | H46: 1270.9 | I46: 1289.79 | J46: 23426.13 | K46: 0
A47: 1200 | C47: 6603 | D47: S | F47: google | G47: 0 | I47: 6933.18 | K47: 0
A48: 1200 | C48: 6605 | D48: S | F48: Messekosten | G48: 0 | I48: 2561.6 | K48: 0
A49: 1200 | C49: 6610 | D49: S | F49: Geschenke abzugsfähig ohne § 37b EStG | G49: 187.77 | I49: 4954.9 | K49: 0
A50: 1200 | C50: 6621 | D50: S | F50: Geschenke n. abzugsfähig mit § 37b EStG | G50: 715.74 | I50: 783.51 | K50: 0
A51: 1200 | C51: 6640 | D51: S | F51: Bewirtungskosten | G51: 0 | I51: 667.66 | K51: 0
A52: 1200 | C52: 6643 | D52: S | F52: Aufmerksamkeiten | G52: 330.42 | I52: 1166.02 | K52: 0
A53: 1200 | C53: 6644 | D53: S | F53: Nicht abzugsfähige Bewirtungskosten | G53: 0 | I53: 286.14 | K53: 0
A54: 1200 | C54: 6645 | D54: S | F54: Nicht abzugsfähige Betriebsausgaben | G54: 0 | I54: 74.54 | K54: 0
A55: 1200 | C55: 6650 | D55: S | F55: Reisekosten Arbeitnehmer | G55: 0 | I55: 29.37 | K55: 0
A56: 1200 | C56: 6652 | D56: S | F56: Mietwagen | G56: 36.97 | I56: 135.92 | K56: 0
A57: 1200 | C57: 6660 | D57: S | F57: Reisekosten AN Übernachtungsaufwand | G57: 0 | I57: 2488.3 | K57: 0
A58: 1200 | C58: 6662 | D58: S | F58: Sonstige Reisekosten | G58: 0 | I58: 1688.8 | K58: 0
... A60: 1200 | C60: 6664 | D60: S | F60: Reisekosten AN Verpfleg.mehraufwand | G60: 0 | I60: 217.8 | K60: 0
A61: 1200 | C61: 0
A62: 1220 | B62: Kosten Warenabgabe | C62: 6780 | D62: S | F62: Fremdarbeiten (Vertrieb) | G62: 31111.11 | H62: 40808.74 | I62: 325002.99 | J62: 577945.42 | K62: 0
A63: 1220 | C63: 6781 | D63: S | F63: Fremdarbeiten (Marketing) | G63: 7958.63 | I63: 83291.18 | K63: 0
A64: 1220 | C64: 6782 | D64: S | F64: Fremdarbeit | G64: 1739 | I64: 169651.25 | K64: 0
A65: 1220 | C65: 0
A66: 1240 | B66: Abschreibungen | C66: 6201 | D66: S | F66: Abschreibung selbst geschaffene imm. VG | G66: 15726.33 | H66: 16358.26 | I66: 188715.96 | J66: 195361.89 | K66: 0
A67: 1240 | C67: 6220 | D67: S | F67: Abschreibungen auf Sachanlagen | G67: 70 | I67: 840 | K67: 0
A68: 1240 | C68: 6280 | D68: S | F68: Forderungsverluste | G68: 561.93 | I68: 561.93 | K68: 0
A69: 1240 | C69: 6936 | D69: S | F69: Forderungsverluste 19% USt | G69: 0 | I69: 5244 | K69: 0
A70: 1240 | C70: 0
A71: 1260 | B71: Sonstige Kosten | C71: 6303 | D71: S | F71: Fremdleistungen und Fremdarbeiten | G71: 12400 | H71: 43962.28 | I71: 148800 | J71: 428128.9 | K71: 0
A72: 1260 | C72: 6800 | D72: S | F72: Porto | G72: 210.44 | I72: 339.38 | K72: 0
A73: 1260 | C73: 6805 | D73: S | F73: Telefon | G73: 828.22 | I73: 11137.98 | K73: 0
A74: 1260 | C74: 6811 | D74: S | F74: Hosting | G74: 8348.03 | I74: 74519.44 | K74: 0
A75: 1260 | C75: 6815 | D75: S | F75: Bürobedarf | G75: 10.91 | I75: 27.85 | K75: 0
A76: 1260 | C76: 6821 | D76: S | F76: Fortbildungskosten | G76: 225 | I76: 450 | K76: 0
A77: 1260 | C77: 6825 | D77: S | F77: Rechts- und Beratungskosten | G77: 903.3 | I77: 9277.1 | K77: 0
A78: 1260 | C78: 6826 | D78: S | F78: Beratungskosten | G78: 16583.37 | I78: 141106.79 | K78: 0
A79: 1260 | C79: 6827 | D79: S | F79: Abschluss- und Prüfungskosten | G79: 580 | I79: 7049.1 | K79: 0
A80: 1260 | C80: 6830 | D80: S | F80: Buchführungskosten | G80: 1900 | I80: 22800 | K80: 0
A81: 1260 | C81: 6850 | D81: S | F81: Sonstiger Betriebsbedarf | G81: 100 | I81: 1200 | K81: 0
A82: 1260 | C82: 6852 | D82: S | F82: Teambuilding | G82: 114 | I82: 532.65 | K82: 0
A83: 1260 | C83: 6855 | D83: S | F83: Nebenkosten des Geldverkehrs | G83: 1759.01 | I83: 10672.12 | K83: 0
A84: 1260 | C84: 6880 | D84: S | F84: Aufwendungen aus Währungsumrechnungen | G84: 0 | I84: 216.49 | K84: 0
A85: 1260 | C85: 0
A86: 1280 | B86: Gesamtkosten | C86: 0 | E86: 1100 | F86: Personalkosten | G86: 52055.99 | H86: 164006.82 | I86: 606428.88 | J86: 1941547.1 | K86: 1
A87: 1280 | C87: 0 | E87: 1150 | F87: Versich./Beiträge | G87: 8134.82 | I87: 89299.95 | K87: 1
A88: 1280 | C88: 0 | E88: 1180 | F88: Fahrzeugko. (o. St) | G88: 1415.83 | I88: 20955.98 | K88: 1
A89: 1280 | C89: 0 | E89: 1200 | F89: Werbe-/Reisekosten | G89: 1270.9 | I89: 23426.13 | K89: 1
A90: 1280 | C90: 0 | E90: 1220 | F90: Kosten Warenabgabe | G90: 40808.74 | I90: 577945.42 | K90: 1
A91: 1280 | C91: 0 | E91: 1240 | F91: Abschreibungen | G91: 16358.26 | I91: 195361.89 | K91: 1
A92: 1280 | C92: 0 | E92: 1260 | F92: Sonstige Kosten | G92: 43962.28 | I92: 428128.9 | K92: 1
A93: 1280 | C93: 0
A94: 1300 | B94: Betriebsergebnis | C94: 0 | E94: 1092 | F94: Betriebl. Rohertrag | G94: 179909.74 | H94: 15902.92 | I94: 1591153.4 | J94: -350393.74 | K94: 2
A95: 1300 | C95: 0 | E95: 1280 | F95: Gesamtkosten | G95: 164006.82 | I95: 1941547.1 | K95: 2
A96: 1300 | C96: 0
A97: 1312 | B97: Sonst. neutr. Aufw | C97: 6969 | D97: S | F97: Sonstige Aufwendungen unregelmäßig | G97: 26246.55 | H97: 26246.55 | I97: 26246.55 | J97: 26246.55 | K97: 0
A98: 1312 | C98: 0
A99: 1320 | B99: Neutraler Aufwand | C99: 0 | E99: 1312 | F99: Sonst. neutr. Aufw | G99: 26246.55 | H99: 26246.55 | I99: 26246.55 | J99: 26246.55 | K99: 1
A100: 1320 | C100: 0
A101: 1322 | B101: Zinserträge | C101: 7100 | D101: H | F101: Sonstige Zinsen und ähnliche Erträge | G101: 0 | H101: 0 | I101: 21.1 | J101: 21.1 | K101: 0
...

Sheet Kostenstellen
A1: Kostenstelle/-träger | B1: Kurzbezeichnung | C1: Langbezeichnung | D1: Verantwortlicher
A2: 200 | B2: aqua | C2: Gemeinkosten aqua cloud
A3: 201 | B3: indirekte | C3: inderekte Kosten
A4: 202 | B4: Recruiting | C4: Recruiting
A5: 210 | B5: Dev | C5: Development
A6: 220 | B6: Product | C6: Product
A7: 230 | B7: Sales | C7: Sales
A8: 235 | B8: Marketing | C8: Marketing
A9: 240 | B9: Ranorex | C9: Ranorex
A10: 2001 | B10: Koch Martin | C10: Koch Martin
A11: 2003 | B11: Mann | C11: Mann
A12: 2011 | B12: Elsner | C12: Elsner Paul
A13: 2012 | B13: Weingartz | C13: Weingartz Robert
... A17: 2018 | B17: Ali Lara | C17: Ali Lara
